bootstrap.py
buildout.cfg
setup.py
alchemist/__init__.py
alchemist.security.egg-info/PKG-INFO
alchemist.security.egg-info/SOURCES.txt
alchemist.security.egg-info/dependency_links.txt
alchemist.security.egg-info/namespace_packages.txt
alchemist.security.egg-info/not-zip-safe
alchemist.security.egg-info/requires.txt
alchemist.security.egg-info/top_level.txt
alchemist/security/__init__.py
alchemist/security/auth.py
alchemist/security/interfaces.py
alchemist/security/permission.py
alchemist/security/permission.txt
alchemist/security/role.py
alchemist/security/role.txt
alchemist/security/schema.py
alchemist/security/tests.py