Metadata-Version: 1.0
Name: alchemist.security
Version: 0.4.2
Summary: Relational Implementation of Zope Security components
Home-page: UNKNOWN
Author: Kapil Thangavelu
Author-email: kapil.foss@gmail.com
License: ZPL
Keywords: zope zope3
Platform: UNKNOWN
Classifier: Programming Language :: Python
Classifier: Environment :: Web Environment
Classifier: License :: OSI Approved :: Zope Public License
Classifier: Topic :: Internet :: WWW/HTTP :: WSGI :: Application
Classifier: Framework :: Zope3
